terminal_extensions/__init__.py
terminal_extensions/cli.py
terminal_extensions-0.1.0.dist-info/LICENSE
terminal_extensions-0.1.0.dist-info/METADATA
terminal_extensions-0.1.0.dist-info/WHEEL
terminal_extensions-0.1.0.dist-info/entry_points.txt
terminal_extensions-0.1.0.dist-info/RECORD
