Metadata-Version: 2.3
Name: terminal-extensions
Version: 0.1.0
Summary: A library for extending terminal environments with custom hooks
License: MIT
Keywords: terminal,extensions,cli
Author: Your Name
Author-email: your.email@example.com
Requires-Python: >=3.7
Classifier: Development Status :: 3 - Alpha
Classifier: Intended Audience :: Developers
Classifier: License :: OSI Approved :: MIT License
Classifier: Programming Language :: Python :: 3
Classifier: Programming Language :: Python :: 3.7
Classifier: Programming Language :: Python :: 3.8
Classifier: Programming Language :: Python :: 3.9
Classifier: Programming Language :: Python :: 3.10
Classifier: Programming Language :: Python :: 3.11
Classifier: Programming Language :: Python :: 3.12
Provides-Extra: dev
Provides-Extra: docs
Provides-Extra: lint
Provides-Extra: test
Requires-Dist: black (>=22.0) ; extra == "dev"
Requires-Dist: black (>=22.0) ; extra == "lint"
Requires-Dist: build ; extra == "dev"
Requires-Dist: mkdocs ; extra == "dev"
Requires-Dist: mkdocs ; extra == "docs"
Requires-Dist: mkdocs-material ; extra == "dev"
Requires-Dist: mkdocs-material ; extra == "docs"
Requires-Dist: mkdocstrings[python] ; extra == "dev"
Requires-Dist: mkdocstrings[python] ; extra == "docs"
Requires-Dist: mypy (>=0.950) ; extra == "dev"
Requires-Dist: mypy (>=0.950) ; extra == "lint"
Requires-Dist: pre-commit ; extra == "dev"
Requires-Dist: pre-commit ; extra == "lint"
Requires-Dist: pytest (>=7.0) ; extra == "dev"
Requires-Dist: pytest (>=7.0) ; extra == "test"
Requires-Dist: pytest-asyncio ; extra == "dev"
Requires-Dist: pytest-asyncio ; extra == "test"
Requires-Dist: ruff ; extra == "dev"
Requires-Dist: ruff ; extra == "lint"
Requires-Dist: twine ; extra == "dev"
Requires-Dist: types-Markdown ; extra == "dev"
Requires-Dist: types-PyYAML ; extra == "dev"
Requires-Dist: types-click ; extra == "dev"
Requires-Dist: types-requests ; extra == "dev"
Project-URL: Documentation, https://github.com/swecc/terminal-extensions#readme
Project-URL: Homepage, https://github.com/swecc/terminal-extensions
Project-URL: Issues, https://github.com/swecc/terminal-extensions/issues
